openplc_editor/Beremiz.py
openplc_editor/BeremizIDE.py
openplc_editor/Beremiz_service.py
openplc_editor/CONTRIBUTING.md
openplc_editor/CodeFileTreeNode.py
openplc_editor/ConfigTreeNode.py
openplc_editor/IDEFrame.py
openplc_editor/NativeLib.py
openplc_editor/NativeLib.xml
openplc_editor/PLCControler.py
openplc_editor/PLCGenerator.py
openplc_editor/PLCOpenEditor.py
openplc_editor/POULibrary.py
openplc_editor/PSKManagement.py
openplc_editor/ProjectController.py
openplc_editor/README.md
openplc_editor/__init__.py
openplc_editor/bitbucket-pipelines.yml
openplc_editor/diff_from_beremiz.txt
openplc_editor/features.py
openplc_editor/version.py
openplc_editor/bacnet/BacnetSlaveEditor.py
openplc_editor/bacnet/__init__.py
openplc_editor/bacnet/bacnet.py
openplc_editor/c_ext/CFileEditor.py
openplc_editor/c_ext/__init__.py
openplc_editor/c_ext/c_ext.py
openplc_editor/canfestival/NetworkEditor.py
openplc_editor/canfestival/SlaveEditor.py
openplc_editor/canfestival/__init__.py
openplc_editor/canfestival/canfestival.py
openplc_editor/canfestival/cf_runtime.c
openplc_editor/canfestival/config_utils.py
openplc_editor/connectors/ConnectorBase.py
openplc_editor/connectors/PYRO_dialog.py
openplc_editor/connectors/SchemeEditor.py
openplc_editor/connectors/WAMP_dialog.py
openplc_editor/connectors/__init__.py
openplc_editor/connectors/PYRO/PSK_Adapter.py
openplc_editor/connectors/PYRO/__init__.py
openplc_editor/connectors/WAMP/__init__.py
openplc_editor/controls/CustomEditableListBox.py
openplc_editor/controls/CustomGrid.py
openplc_editor/controls/CustomIntCtrl.py
openplc_editor/controls/CustomStyledTextCtrl.py
openplc_editor/controls/CustomTable.py
openplc_editor/controls/CustomToolTip.py
openplc_editor/controls/CustomTree.py
openplc_editor/controls/DiscoveryPanel.py
openplc_editor/controls/DurationCellEditor.py
openplc_editor/controls/EnhancedStatusBar.py
openplc_editor/controls/FolderTree.py
openplc_editor/controls/IDBrowser.py
openplc_editor/controls/LibraryPanel.py
openplc_editor-1.1.11.dist-info/LICENSE
openplc_editor-1.1.11.dist-info/METADATA
openplc_editor-1.1.11.dist-info/WHEEL
openplc_editor-1.1.11.dist-info/top_level.txt
openplc_editor-1.1.11.dist-info/RECORD
